pyspamhauscli/__init__.py
pyspamhauscli/pyspamhauscli.py
pyspamhauscli/requirements.txt
pyspamhauscli-1.2.dist-info/METADATA
pyspamhauscli-1.2.dist-info/WHEEL
pyspamhauscli-1.2.dist-info/entry_points.txt
pyspamhauscli-1.2.dist-info/top_level.txt
pyspamhauscli-1.2.dist-info/RECORD
